[
{"id":1,"q":"How many kilometres is it from London to Edinburgh by road (approximately)?","a":667,"unit":"km"},
{"id":2,"q":"What is the population of the United Kingdom (2021 census)?","a":67026292,"unit":"people"},
{"id":3,"q":"What is the population of London (Greater London, 2021)?","a":8799800,"unit":"people"},
{"id":4,"q":"How tall in metres is Ben Nevis, the highest mountain in the UK?","a":1345,"unit":"metres"},
{"id":5,"q":"How long in kilometres is the River Thames?","a":346,"unit":"km"},
{"id":6,"q":"How long in kilometres is the River Severn, the longest river in the UK?","a":354,"unit":"km"},
{"id":7,"q":"What is the area of the United Kingdom in square kilometres?","a":242495,"unit":"sq km"},
{"id":8,"q":"What is the depth in metres of the deepest point of Loch Ness?","a":230,"unit":"metres"},
{"id":9,"q":"How many countries are in the United Kingdom?","a":4,"unit":"countries"},
{"id":10,"q":"What is the distance in kilometres from London to Paris?","a":344,"unit":"km"},
{"id":11,"q":"What is the distance in kilometres from London to New York by air?","a":5540,"unit":"km"},
{"id":12,"q":"How tall in metres is Mount Everest?","a":8849,"unit":"metres"},
{"id":13,"q":"How deep in metres is the Mariana Trench at its deepest point?","a":11034,"unit":"metres"},
{"id":14,"q":"What is the population of China (approximately, 2023)?","a":1412000000,"unit":"people"},
{"id":15,"q":"What is the population of India (approximately, 2023)?","a":1428000000,"unit":"people"},
{"id":16,"q":"What is the area of Russia in square kilometres?","a":17098242,"unit":"sq km"},
{"id":17,"q":"What is the area of Australia in square kilometres?","a":7692024,"unit":"sq km"},
{"id":18,"q":"How long in kilometres is the Amazon River?","a":6400,"unit":"km"},
{"id":19,"q":"How long in kilometres is the Nile River?","a":6650,"unit":"km"},
{"id":20,"q":"What is the height in metres of the Eiffel Tower?","a":330,"unit":"metres"},
{"id":21,"q":"What is the population of France (approximately, 2023)?","a":68000000,"unit":"people"},
{"id":22,"q":"What is the area of England in square kilometres?","a":130395,"unit":"sq km"},
{"id":23,"q":"What is the area of Scotland in square kilometres?","a":78387,"unit":"sq km"},
{"id":24,"q":"What is the area of Wales in square kilometres?","a":20779,"unit":"sq km"},
{"id":25,"q":"How deep in metres is Lake Baikal, the world's deepest lake?","a":1642,"unit":"metres"},
{"id":26,"q":"What is the length of the Eurotunnel (Channel Tunnel) in kilometres?","a":50,"unit":"km"},
{"id":27,"q":"What is the population of Germany (approximately, 2023)?","a":84000000,"unit":"people"},
{"id":28,"q":"What is the height in metres of the Shard skyscraper in London?","a":310,"unit":"metres"},
{"id":29,"q":"How many metres above sea level is the capital city of Bolivia, La Paz?","a":3640,"unit":"metres"},
{"id":30,"q":"What is the approximate length in kilometres of the Great Wall of China?","a":21196,"unit":"km"},
{"id":31,"q":"How many metres tall is Snowdon, the highest mountain in Wales?","a":1085,"unit":"metres"},
{"id":32,"q":"How many metres tall is Scafell Pike, the highest mountain in England?","a":978,"unit":"metres"},
{"id":33,"q":"What is the population of Birmingham, the UK's second-largest city (2021)?","a":1144919,"unit":"people"},
{"id":34,"q":"How long in kilometres is the coastline of the United Kingdom?","a":17820,"unit":"km"},
{"id":35,"q":"How many metres long is the Humber Bridge?","a":2220,"unit":"metres"},
{"id":36,"q":"What is the area of the Sahara Desert in square kilometres?","a":9200000,"unit":"sq km"},
{"id":37,"q":"How many countries are there in Africa?","a":54,"unit":"countries"},
{"id":38,"q":"How many countries are in the world?","a":195,"unit":"countries"},
{"id":39,"q":"What is the area of the United States in square kilometres?","a":9834000,"unit":"sq km"},
{"id":40,"q":"What is the population of the United States (approximately, 2023)?","a":335000000,"unit":"people"},
{"id":41,"q":"How long in kilometres is the Trans-Siberian Railway?","a":9289,"unit":"km"},
{"id":42,"q":"What is the elevation in metres of the Kilimanjaro, Africa's highest peak?","a":5895,"unit":"metres"},
{"id":43,"q":"How many miles is the distance from Land's End to John o' Groats?","a":874,"unit":"miles"},
{"id":44,"q":"What is the width in kilometres of the English Channel at its narrowest point?","a":34,"unit":"km"},
{"id":45,"q":"How many metres tall is the BT Tower in London?","a":177,"unit":"metres"},
{"id":46,"q":"What is the population of Scotland (2021 census)?","a":5480000,"unit":"people"},
{"id":47,"q":"How many kilometres long is the M25 motorway?","a":188,"unit":"km"},
{"id":48,"q":"What is the average depth in metres of the North Sea?","a":95,"unit":"metres"},
{"id":49,"q":"How many square kilometres is Greater London?","a":1572,"unit":"sq km"},
{"id":50,"q":"What is the height in metres of the Empire State Building?","a":443,"unit":"metres"},
{"id":51,"q":"How many kilometres from north to south does the United Kingdom span?","a":965,"unit":"km"},
{"id":52,"q":"What is the population of Wales (2021 census)?","a":3100000,"unit":"people"},
{"id":53,"q":"How long in kilometres is the River Clyde?","a":176,"unit":"km"},
{"id":54,"q":"What is the area of Canada in square kilometres?","a":9985000,"unit":"sq km"},
{"id":55,"q":"How many UNESCO World Heritage Sites are in the United Kingdom?","a":33,"unit":"sites"},
{"id":56,"q":"What is the population of Australia (approximately, 2023)?","a":26000000,"unit":"people"},
{"id":57,"q":"What is the height in metres of the Burj Khalifa, the world's tallest building?","a":828,"unit":"metres"},
{"id":58,"q":"How many metres tall is the London Eye?","a":135,"unit":"metres"},
{"id":59,"q":"What is the depth in metres of Loch Lomond at its deepest?","a":190,"unit":"metres"},
{"id":60,"q":"How many square kilometres is the Lake District National Park?","a":2362,"unit":"sq km"}
]
